{
  "apiVersion": "1.0",
  "swaggerVersion": "1.2",
  "basePath": "https://pure-caverns-73223.herokuapp.com",
  "resourcePath": "welcome",
  "apis": [
    {
      "path": "/v1/greetings",
      "operations": [
        {
          "summary": "Fetches all User items",
          "notes": "This lists all the active users",
          "responseMessages": [
            {
              "code": 200,
              "responseModel": null,
              "message": "Success"
            },
            {
              "code": 401,
              "responseModel": null,
              "message": "Unauthorized"
            },
            {
              "code": 406,
              "responseModel": null,
              "message": "The request you made is not acceptable"
            }
          ],
          "nickname": "Welcome#index",
          "method": "get"
        }
      ]
    },
    {
      "path": "/v1/greetings/{id}",
      "operations": [
        {
          "summary": "Creates all User items",
          "notes": "Creates an active users",
          "responseMessages": [
            {
              "code": 200,
              "responseModel": null,
              "message": "Success"
            },
            {
              "code": 401,
              "responseModel": null,
              "message": "Unauthorized"
            },
            {
              "code": 406,
              "responseModel": null,
              "message": "The request you made is not acceptable"
            }
          ],
          "nickname": "Welcome#create",
          "method": "post"
        }
      ]
    }
  ],
  "authorizations": null
}